setup.py
pyramid_basicauth/__init__.py
pyramid_basicauth.egg-info/PKG-INFO
pyramid_basicauth.egg-info/SOURCES.txt
pyramid_basicauth.egg-info/dependency_links.txt
pyramid_basicauth.egg-info/not-zip-safe
pyramid_basicauth.egg-info/requires.txt
pyramid_basicauth.egg-info/top_level.txt